README.md
setup.py
ddemblem/Base.py
ddemblem/Engine.py
ddemblem/Proxy.py
ddemblem/__init__.py
ddemblem.egg-info/PKG-INFO
ddemblem.egg-info/SOURCES.txt
ddemblem.egg-info/dependency_links.txt
ddemblem.egg-info/not-zip-safe
ddemblem.egg-info/top_level.txt