Metadata-Version: 1.1
Name: ddemblem
Version: 2020.4.14
Summary: 一个用于Bilibili粉丝勋章经验爬取的简单工具
Home-page: https://github.com/BYOUINZAKA/DD-Emblem
Author: BYOUINZAKA
Author-email: 2606675531@qq.com
License: MIT
Platform: UNKNOWN
Classifier: License :: OSI Approved :: MIT License
Classifier: Programming Language :: Python
Classifier: Operating System :: OS Independent
